[
    {
        "title": "To Kill a Mockingbird",
        "published": 1960,
        "genre": "Fiction"
    },
    {
        "title": "1984",
        "published": 1949,
        "genre": "Dystopian"
    },
    {
        "title": "The Great Gatsby",
        "published": 1925,
        "genre": "Fiction"
    },
    {
        "title": "Pride and Prejudice",
        "published": 1813,
        "genre": "Romance"
    },
    {
        "title": "Harry Potter and the Philosopher's Stone",
        "published": 1997,
        "genre": "Fantasy"
    }
]
